clustermolepy/__init__.py
clustermolepy/enrichr.py
clustermolepy/utils.py
clustermolepy-0.3.1.dist-info/licenses/LICENSE
tests/__init__.py
tests/test_enrichr.py
tests/test_utils.py
clustermolepy-0.3.1.dist-info/METADATA
clustermolepy-0.3.1.dist-info/WHEEL
clustermolepy-0.3.1.dist-info/top_level.txt
clustermolepy-0.3.1.dist-info/RECORD
