Metadata-Version: 2.4
Name: clustermolepy
Version: 0.3.1
Summary: Cluster annotation helper for single-cell RNA-seq data in Python
Author-email: Nikhil Mark Lakra <nikhilmarklakra@gmail.com>
License: MIT
Classifier: Development Status :: 3 - Alpha
Classifier: Intended Audience :: Science/Research
Classifier: License :: OSI Approved :: MIT License
Classifier: Programming Language :: Python :: 3.10
Classifier: Topic :: Scientific/Engineering :: Bio-Informatics
Requires-Python: >=3.10
License-File: LICENSE
Requires-Dist: pandas
Requires-Dist: requests
Requires-Dist: biomart
Requires-Dist: anndata
Requires-Dist: numpy
Provides-Extra: dev
Requires-Dist: flake8; extra == "dev"
Requires-Dist: isort; extra == "dev"
Requires-Dist: black; extra == "dev"
Requires-Dist: mypy; extra == "dev"
Requires-Dist: scanpy; extra == "dev"
Requires-Dist: jupyter; extra == "dev"
Dynamic: license-file
